{"lastUsed":1575334596739,"path":"\/Users\/owner\/Desktop\/Projects\/Java_Stack\/Spring_Java","projectCount":1,"recentFiles":[{"path":"\/Strings\/src\/main\/java\/com\/example\/demo","parentWorkspace":"\/Users\/owner\/Desktop\/Projects\/Java_Stack\/Spring_Java","name":"StringsApplication.java","lastModified":1575333906526,"locationURI":"file:\/Users\/owner\/Desktop\/Projects\/Java_Stack\/Spring_Java\/Strings\/src\/main\/java\/com\/example\/demo\/StringsApplication.java"},{"path":"\/Strings\/src\/main\/java\/com\/example\/demo","parentWorkspace":"\/Users\/owner\/Desktop\/Projects\/Java_Stack\/Spring_Java","name":"HelloPage.java","lastModified":1575334596740,"locationURI":"file:\/Users\/owner\/Desktop\/Projects\/Java_Stack\/Spring_Java\/Strings\/src\/main\/java\/com\/example\/demo\/HelloPage.java"}]}